chestnut/__init__.py
chestnut/middleware.py
chestnut/http/__init__.py
chestnut/http/request.py
chestnut/http/response.py
chestnut/layers/__init__.py
chestnut/layers/aws.py
chestnut/layers/azure.py
chestnut/layers/framework.py
chestnut/layers/gcp.py
chestnut-1.1.0.dist-info/LICENSE
chestnut-1.1.0.dist-info/METADATA
chestnut-1.1.0.dist-info/WHEEL
chestnut-1.1.0.dist-info/top_level.txt
chestnut-1.1.0.dist-info/RECORD
