Metadata-Version: 2.1
Name: chestnut
Version: 1.1.0
Summary: Framework to develop multi cloud APIs.
Home-page: https://github.com/Claudjos/chestnut
Author: Claudjos
Author-email: claudjosmail@gmail.com
Keywords: Web App,Multi Cloud
License-File: LICENSE
Requires-Dist: pyfir <1.0.0,>=0.0.5
